{
  "lines": [
    {
      "text": "Ishkuva bhala hai",
      "time": "00:00",
      "start_ms": 0,
      "end_ms": 2000
    },
    {
      "text": "Ishkuva bhala hai",
      "time": "00:04",
      "start_ms": 4440,
      "end_ms": 6080
    },
    {
      "text": "Jis ko chhoa isne wo jana hai",
      "time": "00:06",
      "start_ms": 6080,
      "end_ms": 8960
    },
    {
      "text": "This is my song I had, I will sing it once upon a time Mumbai again",
      "time": "00:10",
      "start_ms": 10040,
      "end_ms": 12680
    },
    {
      "text": "This what you have done?",
      "time": "00:14",
      "start_ms": 14200,
      "end_ms": 16200
    },
    {
      "text": "If you sit down, then it hurts",
      "time": "00:17",
      "start_ms": 17480,
      "end_ms": 19480
    },
    {
      "text": "If you sit down, then it hurts",
      "time": "00:20",
      "start_ms": 20280,
      "end_ms": 22280
    },
    {
      "text": "If you sit down, then it hurts",
      "time": "00:23",
      "start_ms": 23160,
      "end_ms": 25160
    },
    {
      "text": "Ishkuva bhala hai",
      "time": "00:27",
      "start_ms": 27920,
      "end_ms": 29920
    },
    {
      "text": "Jis ko chhoa isne wo jana hai",
      "time": "00:30",
      "start_ms": 30480,
      "end_ms": 33280
    },
    {
      "text": "Dilse ho ta hai",
      "time": "00:33",
      "start_ms": 33960,
      "end_ms": 34960
    },
    {
      "text": "Shurup par kambak tasar pe chana hai",
      "time": "00:34",
      "start_ms": 34960,
      "end_ms": 37680
    },
    {
      "text": "Kha bhi khutze",
      "time": "00:38",
      "start_ms": 38519,
      "end_ms": 39440
    },
    {
      "text": "Kha bhi khudze",
      "time": "00:39",
      "start_ms": 39440,
      "end_ms": 40760
    },
    {
      "text": "Kha bhi zamanne se lada hai",
      "time": "00:40",
      "start_ms": 40760,
      "end_ms": 43040
    },
    {
      "text": "Ithna gha bha badna mo bher bi",
      "time": "00:44",
      "start_ms": 44120,
      "end_ms": 47980
    },
    {
      "text": "Har zaba pe ada hai",
      "time": "00:48",
      "start_ms": 48379,
      "end_ms": 51440
    },
    {
      "text": "Ishkuva bhala hai",
      "time": "00:52",
      "start_ms": 52280,
      "end_ms": 55120
    },
    {
      "text": "Aakitaria",
      "time": "00:58",
      "start_ms": 58120,
      "end_ms": 59160
    },
    {
      "text": "I'm in love with you, why are you in love with me?",
      "time": "02:00",
      "start_ms": 120000,
      "end_ms": 123680
    },
    {
      "text": "What did you do?",
      "time": "02:03",
      "start_ms": 123680,
      "end_ms": 126280
    },
    {
      "text": "All the world is alive, I'm here",
      "time": "02:06",
      "start_ms": 126280,
      "end_ms": 131080
    },
    {
      "text": "You're here, I'm in love with you",
      "time": "02:11",
      "start_ms": 131080,
      "end_ms": 134160
    },
    {
      "text": "What did you do?",
      "time": "02:14",
      "start_ms": 134160,
      "end_ms": 135760
    },
    {
      "text": "I'm in love with you, when I take you from me",
      "time": "02:17",
      "start_ms": 137920,
      "end_ms": 142880
    },
    {
      "text": "I'm in love with you",
      "time": "02:22",
      "start_ms": 142880,
      "end_ms": 145400
    },
    {
      "text": "What did you do?",
      "time": "02:25",
      "start_ms": 145400,
      "end_ms": 147800
    },
    {
      "text": "What did you do?",
      "time": "02:27",
      "start_ms": 147800,
      "end_ms": 150880
    },
    {
      "text": "What did you do?",
      "time": "02:57",
      "start_ms": 177800,
      "end_ms": 179800
    },
    {
      "text": "I'm in love with you, why are you in love with me?",
      "time": "03:27",
      "start_ms": 207800,
      "end_ms": 213880
    },
    {
      "text": "I feel a little upset, I feel a little upset",
      "time": "03:33",
      "start_ms": 213880,
      "end_ms": 219240
    },
    {
      "text": "I feel a little upset, what did you do?",
      "time": "03:39",
      "start_ms": 219240,
      "end_ms": 223960
    },
    {
      "text": "I'm in love with you, I'm in love with you",
      "time": "03:43",
      "start_ms": 223960,
      "end_ms": 229120
    },
    {
      "text": "What did you do?",
      "time": "03:49",
      "start_ms": 229120,
      "end_ms": 234280
    },
    {
      "text": "All the world is alive, I'm here",
      "time": "03:54",
      "start_ms": 234560,
      "end_ms": 239320
    },
    {
      "text": "You're here, I'm in love with you",
      "time": "03:59",
      "start_ms": 239320,
      "end_ms": 242600
    },
    {
      "text": "What did you do?",
      "time": "04:02",
      "start_ms": 242600,
      "end_ms": 243960
    },
    {
      "text": "I'm in love with you, when I take you from me",
      "time": "04:03",
      "start_ms": 243960,
      "end_ms": 248920
    },
    {
      "text": "I'm in love with you, what did you do?",
      "time": "04:08",
      "start_ms": 248920,
      "end_ms": 254680
    },
    {
      "text": "I'm in love with you, I'm in love with you",
      "time": "04:24",
      "start_ms": 264400,
      "end_ms": 272799
    },
    {
      "text": "What did you do?",
      "time": "04:32",
      "start_ms": 272799,
      "end_ms": 277200
    },
    {
      "text": "I'm in love with you, where are you?",
      "time": "04:37",
      "start_ms": 277200,
      "end_ms": 284520
    },
    {
      "text": "What did you do?",
      "time": "04:44",
      "start_ms": 284520,
      "end_ms": 287599
    },
    {
      "text": "What did you do?",
      "time": "04:47",
      "start_ms": 287599,
      "end_ms": 290919
    },
    {
      "text": "What did you do?",
      "time": "04:50",
      "start_ms": 290919,
      "end_ms": 293280
    },
    {
      "text": "Neza Parse",
      "time": "05:23",
      "start_ms": 323280,
      "end_ms": 330280
    },
    {
      "text": "Neza Parse",
      "time": "05:32",
      "start_ms": 332280,
      "end_ms": 339280
    },
    {
      "text": "Neza Dada",
      "time": "05:40",
      "start_ms": 340280,
      "end_ms": 345280
    },
    {
      "text": "Va Neza Rini",
      "time": "05:46",
      "start_ms": 346280,
      "end_ms": 352280
    },
    {
      "text": "Neza Parse",
      "time": "05:52",
      "start_ms": 352280,
      "end_ms": 359280
    },
    {
      "text": "Neza Rini",
      "time": "05:59",
      "start_ms": 359280,
      "end_ms": 364280
    },
    {
      "text": "Neza Rini",
      "time": "06:04",
      "start_ms": 364280,
      "end_ms": 369280
    },
    {
      "text": "Neza Rini",
      "time": "06:09",
      "start_ms": 369280,
      "end_ms": 372280
    },
    {
      "text": "Neza Rini",
      "time": "06:12",
      "start_ms": 372280,
      "end_ms": 381280
    },
    {
      "text": "Neza Parse",
      "time": "06:21",
      "start_ms": 381280,
      "end_ms": 403280
    }
  ],
  "metadata": {
    "language": "en",
    "source": "ai_generated",
    "line_count": 55,
    "video_id": "mt-5ZbKqiDc",
    "generated_at": "2026-07-10T03:21:01.908569",
    "duration_seconds": null,
    "model_used": "base"
  },
  "raw_content": null
}